{
  "document_id": "DOC001",
  "title": "Premium Widget Features",
  "category": "Product",
  "content": "Our Premium Widget includes advanced features designed specifically for our most valued customers. With enhanced performance capabilities, exclusive customization options, and priority support access, the Premium Widget delivers exceptional value. Key features include: advanced analytics dashboard, real-time monitoring, custom integrations, dedicated account management, and 24/7 premium support. These features are crafted to meet the sophisticated needs of our Gold-tier customers who demand excellence in every interaction. The Premium Widget represents our commitment to innovation and customer success, providing tools that drive measurable business outcomes.",
  "audience": "High-Value",
  "keywords": ["premium", "features", "upgrade", "exclusive", "gold", "advanced", "analytics"],
  "approval_date": "2025-11-01T00:00:00Z",
  "source_url": "https://example.com/content/premium-widget",
  "metadata": {
    "author": "Marketing Team",
    "version": "1.2",
    "last_updated": "2025-10-15"
  }
}